model/VERSION
model/__init__.py
model/config.yml
model/pipeline.py
model/predict.py
model/train_pipeline.py
model/config/__init__.py
model/config/core.py
model/datasets/__init__.py
model/datasets/test.csv
model/datasets/train.csv
model/processing/__init__.py
model/processing/data_manager.py
model/processing/features.py
model/processing/validation.py
model/trained_models/model_output_v0.1.0.pkl
survival_predictor_model-0.1.0.dist-info/LICENSE
survival_predictor_model-0.1.0.dist-info/METADATA
survival_predictor_model-0.1.0.dist-info/WHEEL
survival_predictor_model-0.1.0.dist-info/top_level.txt
survival_predictor_model-0.1.0.dist-info/RECORD
